datajob/__init__.py
datajob/datajob.py
datajob/datajob_base.py
datajob/datajob_context.py
datajob/datajob_execution_input.py
datajob/datajob_stack.py
datajob/glue/__init__.py
datajob/glue/glue_job.py
datajob/package/__init__.py
datajob/package/wheel.py
datajob/sagemaker/__init__.py
datajob/sagemaker/sagemaker_job.py
datajob/sns/__init__.py
datajob/sns/sns.py
datajob/stepfunctions/__init__.py
datajob/stepfunctions/stepfunctions_execute.py
datajob/stepfunctions/stepfunctions_workflow.py
datajob-0.11.0.dist-info/entry_points.txt
datajob-0.11.0.dist-info/LICENSE
datajob-0.11.0.dist-info/WHEEL
datajob-0.11.0.dist-info/METADATA
datajob-0.11.0.dist-info/RECORD
