Metadata-Version: 2.1
Name: datajob
Version: 0.11.0
Summary: Build and deploy a serverless data pipeline with no effort on AWS.
Home-page: https://github.com/vincentclaes/datajob
License: Apache Software License (Apache 2.0)
Keywords: pipelines,machine learning,data pipelines,data science,data engineering
Author: Vincent Claes
Author-email: vincent.v.claes@gmail.com
Requires-Python: >=3.8,<4.0
Classifier: License :: Other/Proprietary License
Classifier: Programming Language :: Python :: 3
Classifier: Programming Language :: Python :: 3.8
Classifier: Programming Language :: Python :: 3.9
Classifier: Programming Language :: Python :: 3.10
Classifier: Programming Language :: Python :: 3.11
Requires-Dist: aws-cdk.aws-glue (>=1.181,<2.0)
Requires-Dist: aws-cdk.aws-s3-deployment (>=1.181,<2.0)
Requires-Dist: aws-cdk.aws-sns-subscriptions (>=1.181,<2.0)
Requires-Dist: aws-cdk.aws-stepfunctions (>=1.181,<2.0)
Requires-Dist: aws-cdk.core (>=1.181,<2.0)
Requires-Dist: contextvars (>=2.4,<3.0)
Requires-Dist: rich (>=9.13.0,<10.0.0)
Requires-Dist: stepfunctions (>=2.1.0,<3.0.0)
Requires-Dist: toposort (>=1.6,<2.0)
Requires-Dist: typer (>=0.3.2,<0.4.0)
Project-URL: Repository, https://github.com/vincentclaes/datajob
